youtube2midi/__init__.py
youtube2midi/__main__.py
youtube2midi/cli.py
youtube2midi/converter.py
youtube2midi/syn2midi/mask.bmp
youtube2midi/syn2midi/mask88.bmp
youtube2midi/syn2midi/licenses/bzip2.txt
youtube2midi/syn2midi/licenses/celt.txt
youtube2midi/syn2midi/licenses/freetype.txt
youtube2midi/syn2midi/licenses/frei0r.txt
youtube2midi/syn2midi/licenses/gnutls.txt
youtube2midi/syn2midi/licenses/lame.txt
youtube2midi/syn2midi/licenses/libass.txt
youtube2midi/syn2midi/licenses/libgsm.txt
youtube2midi/syn2midi/licenses/libmodplug.txt
youtube2midi/syn2midi/licenses/libtheora.txt
youtube2midi/syn2midi/licenses/libvorbis.txt
youtube2midi/syn2midi/licenses/libvpx.txt
youtube2midi/syn2midi/licenses/midifile.txt
youtube2midi/syn2midi/licenses/nut.txt
youtube2midi/syn2midi/licenses/opencore-amr.txt
youtube2midi/syn2midi/licenses/openjpeg.txt
youtube2midi/syn2midi/licenses/rtmpdump.txt
youtube2midi/syn2midi/licenses/schroedinger.txt
youtube2midi/syn2midi/licenses/speex.txt
youtube2midi/syn2midi/licenses/syn2midi
youtube2midi/syn2midi/licenses/utvideo.txt
youtube2midi/syn2midi/licenses/vo-aacenc.txt
youtube2midi/syn2midi/licenses/vo-amrwbenc.txt
youtube2midi/syn2midi/licenses/x264.txt
youtube2midi/syn2midi/licenses/xavs.txt
youtube2midi/syn2midi/licenses/xvid.txt
youtube2midi/syn2midi/licenses/zlib.txt
youtube2midi/syn2midi/windows/avcodec-54.dll
youtube2midi/syn2midi/windows/avformat-54.dll
youtube2midi/syn2midi/windows/avutil-51.dll
youtube2midi/syn2midi/windows/libgcc_s_dw2-1.dll
youtube2midi/syn2midi/windows/libstdc++-6.dll
youtube2midi/syn2midi/windows/libwinpthread-1.dll
youtube2midi/syn2midi/windows/swscale-2.dll
youtube2midi/syn2midi/windows/syn2midi.exe
youtube2midi-0.1.1.post1.dist-info/LICENSE
youtube2midi-0.1.1.post1.dist-info/METADATA
youtube2midi-0.1.1.post1.dist-info/WHEEL
youtube2midi-0.1.1.post1.dist-info/entry_points.txt
youtube2midi-0.1.1.post1.dist-info/top_level.txt
youtube2midi-0.1.1.post1.dist-info/RECORD
