Metadata-Version: 2.1
Name: youtube2midi
Version: 0.1.1.post1
Summary: A Python module with a small cli, used to automatically download a Synthesia piano tutorial from a YouTube URL and convert it to a MIDI file.
Home-page: https://github.com/Naratna/youtube2midi
Author: Naratna
License: MIT
Download-URL: https://github.com/Naratna/youtube2midi/archive/refs/tags/v0.1.1.post1.tar.gz
Keywords: python,midi,youtube
Platform: UNKNOWN
Classifier: Programming Language :: Python :: 3
Classifier: License :: OSI Approved :: MIT License
Classifier: Operating System :: Microsoft :: Windows
Requires-Dist: youtube-dl
